[
  {
    "id": "mmpm6ow26sv4m177qvd",
    "emojis": [
      "🥦"
    ],
    "donorName": "Anonymous",
    "donationAmount": 45,
    "message": "",
    "createdAt": "2026-03-14T00:55:39.650Z"
  },
  {
    "id": "mmpmix4u06p41ftihxu8",
    "emojis": [
      "🥦"
    ],
    "donorName": "Maurice Jenkins",
    "donationAmount": 0.31,
    "message": "hi",
    "createdAt": "2026-03-14T01:05:10.206Z"
  },
  {
    "id": "mmpn0ldrr94s4ykz9rp",
    "emojis": [
      "🥦"
    ],
    "donorName": "Maurice Jenkins",
    "donationAmount": 0.19,
    "message": "hi",
    "createdAt": "2026-03-14T01:18:54.783Z"
  },
  {
    "id": "mmpnf5thizsp105j83e",
    "emojis": [
      "🥦"
    ],
    "donorName": "Maurice Jenkins",
    "donorEmail": "jenkinsmaurice003@gmail.com",
    "donorPhone": "2243492595",
    "donationAmount": 0.05,
    "message": "hi",
    "createdAt": "2026-03-14T01:30:14.453Z"
  },
  {
    "id": "mmpnk1fpu9izv39wfd",
    "emojis": [
      "🥦"
    ],
    "donorName": "Maurice Jenkins",
    "donorEmail": "jenkinsmaurice003@gmail.com",
    "donorPhone": "",
    "donationAmount": 0.04,
    "message": "hi bro",
    "createdAt": "2026-03-14T01:34:02.053Z"
  }
]